txl_kernel/__init__.py
txl_kernel/driver.py
txl_kernel/message.py
txl_kernel-0.3.8.dist-info/METADATA
txl_kernel-0.3.8.dist-info/WHEEL
txl_kernel-0.3.8.dist-info/licenses/LICENSE.txt
txl_kernel-0.3.8.dist-info/RECORD
